{
  "score_item_id": "c77cedd3-2800-7f7f-964b-88f5c2451e79",
  "clinical_relevance": "O uso de antidiabéticos orais no histórico do paciente indica diabetes mellitus tipo 2 (DM2) estabelecido ou resistência insulínica significativa em tratamento farmacológico. A metformina (biguanida) é o agente de primeira linha mais utilizado, com mecanismos pleitrópicos bem documentados: ativação da AMPK, redução da gliconeogênese hepática, diminuição da lipotoxicidade hepática, aumento do transporte de glicose para o tecido muscular, melhora da sensibilidade insulínica hepática, modulação da microbiota intestinal e melhora da performance mitocondrial. Possui também ação central sobre o apetite (inferida de modelos animais). A dose habitual varia de 500 mg a 2.000 mg/dia; a formulação de liberação prolongada (XR) é frequentemente preferida no jantar, com dose total preferencialmente ≤1.600–1.700 mg/dia fora do contexto de DM2 franco. Em diabéticos estabelecidos, doses até 2 g/dia são utilizadas.\n\nEvidências comparativas mostram que mudança de estilo de vida reduziu o risco de progressão para DM2 em 58%, versus 30% com metformina isolada (estudo de 2002). Um ensaio com três braços (metformina 2 g/dia vs. empagliflozina vs. jejum 5:2 com shake hipocalórico em adultos com DM2 recente, 16 semanas) demonstrou que o jejum 5:2 superou ambos os fármacos em redução de HbA1c e produziu quase o dobro da perda de peso.\n\nOutras classes de antidiabéticos orais relevantes: inibidores de DPP-4 (gliptinas), que bloqueiam a inativação das incretinas (GLP-1, GIP) pelo DPP-4; inibidores de SGLT-2 (gliflozinas, como empagliflozina), com benefícios cardiovasculares e renais estabelecidos; e sulfonilureias/metiglinidas, que estimulam a secreção insulínica com risco de hipoglicemia.\n\nMonitoramento essencial em usuários de antidiabéticos orais:\n- Metformina (uso prolongado): depleção de vitamina B12 — monitorar B12 sérica e homocisteína regularmente; suplementar com B12 sublingual quando necessário. A deficiência de B12 combinada ao uso de inibidores de bomba de prótons pode gerar quadros erroneamente diagnosticados como demência ou depressão em idosos.\n- Função renal: avaliação antes de iniciar/ajustar metformina (contraindicação relativa em insuficiência renal); creatinina sérica e TFG como parâmetros de segurança.\n- Controle glicêmico: HbA1c (meta funcional integrativa ~5,3–5,5%; diagnóstico ≥6,5%; alto risco ≥5,6%), glicemia de jejum (alvo 60–90 mg/dL na abordagem integrativa), insulina de jejum (meta ideal ≤6 µU/mL, estourando 8 em contexto inflamatório), HOMA-IR (alvo <2,15).\n- Estatinas em uso concomitante: podem elevar glicemia de jejum e HbA1c — avaliar impacto metabólico.\n- Sulfonilureias e metiglinidas: risco de hipoglicemia durante exercício físico — orientar monitorização glicêmica, ajuste alimentar e ajuste de dose.\n\nA homocisteína elevada (alvo <7,9 µmol/L) é marcador inflamatório e cardiovascular adicional relevante em diabéticos em uso de metformina pela depleção de B12/folato. O índice TG/HDL (mulheres <1,4; homens <1,2) e o índice TAIG (TG/[glicose/2], meta <8) complementam a estratificação do risco metabólico.\n\nO uso de antidiabéticos orais no histórico representa impacto clínico elevado: DM2 é doença crônica de alta prevalência global (~10% dos adultos), com morbimortalidade cardiovascular expressiva e ampla possibilidade de intervenção terapêutica e de estilo de vida. A otimização farmacológica, associada a estratégias alimentares (low carb, mediterrânea, jejum intermitente), exercício resistido e suplementação integrativa, pode reduzir ou eliminar a necessidade medicamentosa em subgrupos de pacientes.",
  "points": 20,
  "patient_explanation": "Antidiabéticos orais são remédios para controlar o açúcar no sangue em pessoas com diabetes tipo 2. O mais conhecido é a metformina, que ajuda o organismo a usar melhor a insulina e reduz a produção de açúcar pelo fígado.\n\nEsse medicamento deve ser combinado com alimentação saudável e atividade física. Com mudanças consistentes no estilo de vida, muitas vezes é possível reduzir a dose sob orientação médica.\n\nAtenção: o uso prolongado de metformina pode reduzir a absorção de vitamina B12, causando cansaço ou formigamentos. Seu médico pode solicitar exames periódicos e indicar suplementação.\n\nSe você toma sulfonilureias, fique atento a sinais de hipoglicemia (tontura, suor frio, fraqueza) durante exercícios. Acompanhamento médico regular é essencial para ajustar o tratamento.",
  "conduct": "## Avaliação Inicial do Paciente em Uso de Antidiabéticos Orais\n\n### Identificação da Classe em Uso\n- Confirmar o(s) antidiabético(s) oral(is) em uso: metformina, sulfonilureias (glibenclamida, glicazida), metiglinidas, gliptinas (inibidores DPP-4), gliflozinas (inibidores SGLT-2), acarbose\n- Registrar dose, frequência e tempo de uso de cada medicamento\n- Identificar uso concomitante de inibidores de bomba de prótons (IBP) — risco aumentado de depleção de B12\n- Avaliar uso de estatinas (podem elevar glicemia de jejum e HbA1c)\n\n### Investigação Complementar Prioritária\n\n**Controle glicêmico:**\n- HbA1c (meta integrativa ~5,3–5,5%; diagnóstico DM2 ≥6,5%)\n- Glicemia de jejum (alvo integrativo 60–90 mg/dL)\n- Insulina de jejum (meta ≤6 µU/mL; até 8 em contexto inflamatório)\n- HOMA-IR (alvo <2,15) e HOMA-β (referência 167–175)\n- Curva insulinêmica-glicêmica em casos limítrofes ou histórico de efeito sanfona\n- Frutosamina (complementar; reflete ~20 dias)\n\n**Segurança e monitoramento de metformina:**\n- Função renal: creatinina sérica, ureia, TFG estimada — obrigatório antes de iniciar/ajustar dose\n- Vitamina B12 sérica — depleção frequente no uso prolongado\n- Homocisteína (alvo <7,9 µmol/L) — marcador de depleção de B12/folato e risco cardiovascular\n\n**Risco cardiovascular e metabólico:**\n- Perfil lipídico completo: colesterol total, HDL, LDL, triglicerídeos\n- Índice TG/HDL (mulheres <1,4; homens <1,2)\n- Índice TAIG: TG/(glicose/2), meta <8\n- PCR ultrassensível, TNF-α (<8,1), IL-6 (<3,4)\n- LDL oxidada quando disponível\n\n### Conduta Farmacológica\n\n**Metformina:**\n- Dose habitual: 500–2.000 mg/dia; preferência por 1 g no jantar (Glifage XR)\n- Considerar 500–850 mg na primeira refeição conforme grau de resistência insulínica e IMC\n- Limitar a ≤1.600–1.700 mg/dia em não diabéticos; doses maiores apenas em DM2 estabelecido\n- Contraindicação relativa em insuficiência renal — monitorar TFG\n- **Suplementar vitamina B12 sublingual** em uso prolongado ou quando B12/homocisteína alteradas\n\n**Sulfonilureias e metiglinidas:**\n- Orientar monitorização glicêmica antes e durante exercícios físicos\n- Ajustar dieta e dose em dias de atividade intensa para evitar hipoglicemia\n- Considerar substituição por classes com menor risco hipoglicêmico quando possível\n\n**Inibidores de SGLT-2 (gliflozinas):**\n- Avaliar benefícios cardiovasculares e renais adicionais em pacientes de alto risco\n- Em jejum intermitente: discutir ajuste ou omissão de dose com o paciente conforme orientação clínica\n\n**Inibidores de DPP-4 (gliptinas):**\n- Adequados para jejum intermitente (menor risco de hipoglicemia); associar a correções sistêmicas\n\n### Intervenções de Estilo de Vida\n\n**Alimentação:**\n- Dieta low carb ou cetogênica para HbA1c entre 6,5% e 9%: evidências de redução de glicose, HbA1c, triglicerídeos e melhora de HOMA-IR\n- Dieta mediterrânea como alternativa (especialmente com excesso de gordura saturada)\n- Reduzir carga glicêmica: combinar carboidratos com vegetais e proteína; evitar ultraprocessados\n\n**Jejum intermitente:**\n- Protocolo 5:2 superou metformina e empagliflozina em redução de HbA1c e perda de peso em ensaio clínico de 16 semanas\n- Em sulfonilureias/insulina: monitorização glicêmica rigorosa (CGM); ajustar dose nos dias de jejum\n\n**Exercício físico:**\n- Treino resistido com progressão e monitoramento: essencial para saúde metabólica\n- Intervalo training e caminhada intervalada superiores ao exercício contínuo no controle glicêmico em DM2\n\n### Suplementação Integrativa Adjuvante\n- **Berberina HCl**: sensibilizador insulínico antes das refeições — alternativa/adjuvante à metformina\n- **Cromo, vanádio, magnésio, inositol**: moduladores do metabolismo da glicose e sensibilidade insulínica\n- **L-carnitina** (500 mg a 2 g): metanálise de 37 estudos (2019) demonstrou redução de glicemia de jejum, insulina basal e HbA1c\n- **Vitamina B12 sublingual**: obrigatória em uso prolongado de metformina\n- **Gimnema silvestre** (200–300 mg pré-refeição): meta-análise (2021, 10 estudos, N=419) mostrou redução de glicemias, HbA1c, triglicerídeos e colesterol em DM2\n- **Trans-resveratrol, EGCG, ácido alfa-lipoico**: redução de glicação avançada e HbA1c\n\n### Critérios de Encaminhamento e Seguimento\n- **Endocrinologista**: HbA1c persistentemente elevada (>9%) apesar de tratamento otimizado, necessidade de insulinização, hipoglicemias recorrentes\n- **Cardiologista**: risco cardiovascular elevado, especialmente em usuários de SGLT-2 ou histórico de eventos cardiovasculares\n- **Nefrologista**: TFG reduzida com necessidade de ajuste farmacológico\n- **Nutricionista**: suporte para implementação de dieta low carb, cetogênica ou mediterrânea\n- Monitorar HbA1c, glicemia de jejum e insulina trimestralmente; reavaliação de B12 e homocisteína a cada 6–12 meses em usuários de metformina\n- Avaliar redução ou suspensão gradual dos antidiabéticos conforme melhora metabólica comprovada"
}
